Workbook

Sheet Fixed cost calculation
A1: Capacity Factor | B1: 0.8 | C1: 0.8
A2: rate r | B2: 0.1 | C2: 0.09
A3: no of years | B3: 25 | C3: 25
A4: A/P | B4: =(B2*(1+B2)^B3)/((1+B2)^B3-1) -> 0.11016807 | C4: =(C2*(1+C2)^C3)/((1+C2)^C3-1) -> 0.10180625
A5: coal plant factor | B5: 0.8 | C5: 0.8
A7: Plant | B7: average (Fixed O&M (cr. ₹/MW/year) | C7: Fixed Cost in ₹/MWh | D7: CAPEX ( ₹/MW) | E7: Annual CAPEX ( ₹/MW) | F7: Annual CAPEX ( ₹/MWh) | G7: Efficiency | H7: Fuel Price | I7: Heat Rate | J7: CO2 cost | K7: Magrinal cost | L7: Profit Margin | M7: Add.cost in RS/MWh | N7: Marginal | O7: Additional Cost | P7: Variable cost | Q7: Bidding Marginal cost
A8: Coal_1 | B8: 0.22333333 | C8: =(B8*10^7)/(8760*$B$1) -> 318.68341 | D8: 84330423 | E8: =D8*$B$4 -> 9290520.1 | F8: =(E8)/(8760*$B$1) -> 1325.7021 | G8: 0.36 | H8: =ROUND(('Coal Prices'!$C$11/'Coal Prices'!$H$5)/G8*(860000/1000),2) -> 1665.33 | I8: 0 | J8: 0 | K8: =C8+H8+F8 -> 3309.7155 | L8: 0.15 | M8: =C8+F8 -> 1644.3855 | O8: =ROUND((C8+F8)/1000,2) -> 1.64 | P8: =H8/1000 -> 1.66533 | Q8: =K8+L8*K8 -> 3806.1728
A9: Coal_2 (lignite) | B9: 0.25 | C9: =(B9*10^7)/(8760*$B$1) -> 356.73516 | D9: 83003627 | E9: =D9*$B$4 -> 9144349.6 | F9: =(E9)/(8760*$B$1) -> 1304.8444 | G9: 0.3 | H9: =ROUND(('Coal Prices'!$C$11/'Coal Prices'!$H$5)/G9*(860000/1000),2) -> 1998.4 | I9: 0 | J9: 0 | K9: =C9+H9+F9 -> 3659.9796 | L9: 0.11 | M9: =C9+F9 -> 1661.5796 | O9: =ROUND((C9+F9)/1000,2) -> 1.66 | P9: =H9/1000 -> 1.9984 | Q9: =K9+L9*K9 -> 4062.5773
A10: Coal_3 (lignite) | B10: 0.25 | C10: =(B10*10^7)/(8760*$B$1) -> 356.73516 | D10: 83131232 | E10: =D10*$B$4 -> 9158407.6 | F10: =(E10)/(8760*$B$1) -> 1306.8504 | G10: 0.28 | H10: =ROUND(('Coal Prices'!$C$11/'Coal Prices'!$H$17)/G10*(860000/1000),2) -> 2319.57 | I10: 0 | J10: 0 | K10: =C10+H10+F10 -> 3983.1556 | L10: 0.12 | M10: =C10+F10 -> 1663.5856 | O10: =ROUND((C10+F10)/1000,2) -> 1.66 | P10: =H10/1000 -> 2.31957 | Q10: =K10+L10*K10 -> 4461.1342
A11: Coal_4 (imported) | B11: 0.27 | C11: =(B11*10^7)/(8760*$B$1) -> 385.27397 | D11: 91982617 | E11: =D11*$B$4 -> 10133548 | F11: =(E11)/(8760*$B$1) -> 1445.9971 | G11: 0.35 | H11: =ROUND(('Coal Prices'!$C$11/'Coal Prices'!$H$17)/G11*(860000/1000),2) -> 1855.65 | I11: 0 | J11: 0 | K11: =C11+H11+F11 -> 3686.9211 | L11: 0.15 | M11: =C11+F11 -> 1831.2711 | O11: =ROUND((C11+F11)/1000,2) -> 1.83 | P11: =H11/1000 -> 1.85565 | Q11: =K11+L11*K11 -> 4239.9592
A12: Coal_5 | B12: 0.21539064 | C12: =(B12*10^7)/(8760*$B$1) -> 307.34966 | D12: 84882697 | E12: =D12*$B$4 -> 9351363.1 | F12: =(E12)/(8760*$B$1) -> 1334.384 | G12: 0.29 | H12: =ROUND(('Coal Prices'!$C$11/'Coal Prices'!$H$5)/G12*(860000/1000),2) -> 2067.31 | I12: 0 | J12: 0 | K12: =C12+H12+F12 -> 3709.0437 | L12: 0.13 | M12: =C12+F12 -> 1641.7337 | O12: =ROUND((C12+F12)/1000,2) -> 1.64 | P12: =H12/1000 -> 2.06731 | Q12: =K12+L12*K12 -> 4191.2193
A13: Coal_6 | B13: 0.21294529 | C13: =(B13*10^7)/(8760*$B$1) -> 303.86029 | D13: 85195342 | E13: =D13*$B$4 -> 9385806.6 | F13: =(E13)/(8760*$B$1) -> 1339.2989 | G13: 0.31 | H13: =ROUND(('Coal Prices'!$C$11/'Coal Prices'!$H$5)/G13*(860000/1000),2) -> 1933.93 | I13: 0 | J13: 0 | K13: =C13+H13+F13 -> 3577.0892 | L13: 0.12 | M13: =C13+F13 -> 1643.1592 | O13: =ROUND((C13+F13)/1000,2) -> 1.64 | P13: =H13/1000 -> 1.93393 | Q13: =K13+L13*K13 -> 4006.3399
A14: Coal_7 | B14: 0.25544861 | C14: =(B14*10^7)/(8760*$B$1) -> 364.51 | D14: 85448559 | E14: =D14*$B$4 -> 9413703 | F14: =(E14)/(8760*$B$1) -> 1343.2795 | G14: 0.38 | H14: =ROUND(('Coal Prices'!$C$11/'Coal Prices'!$H$5)/G14*(860000/1000),2) -> 1577.68 | I14: 0 | J14: 0 | K14: =C14+H14+F14 -> 3285.4695 | L14: 0.13 | M14: =C14+F14 -> 1707.7895 | O14: =ROUND((C14+F14)/1000,2) -> 1.71 | P14: =H14/1000 -> 1.57768 | Q14: =K14+L14*K14 -> 3712.5806
A15: Coal_8 | B15: 0.25424885 | C15: =(B15*10^7)/(8760*$B$1) -> 362.79801 | D15: 85851440 | E15: =D15*$B$4 -> 9458087.6 | F15: =(E15)/(8760*$B$1) -> 1349.613 | G15: 0.37 | H15: =ROUND(('Coal Prices'!$C$11/'Coal Prices'!$H$5)/G15*(860000/1000),2) -> 1620.32 | I15: 0 | J15: 0 | K15: =C15+H15+F15 -> 3332.731 | L15: 0.13 | M15: =C15+F15 -> 1712.411 | O15: =ROUND((C15+F15)/1000,2) -> 1.71 | P15: =H15/1000 -> 1.62032 | Q15: =K15+L15*K15 -> 3765.986
A16: Coal_9 | B16: 0.20581826 | C16: =(B16*10^7)/(8760*$B$1) -> 293.69045 | D16: 87649405 | E16: =D16*$B$4 -> 9656166 | F16: =(E16)/(8760*$B$1) -> 1377.8776 | G16: 0.37 | H16: =ROUND(('Coal Prices'!$C$11/'Coal Prices'!$H$5)/G16*(860000/1000),2) -> 1620.32 | I16: 0 | J16: 0 | K16: =C16+H16+F16 -> 3291.888 | L16: 0.13 | M16: =C16+F16 -> 1671.568 | O16: =ROUND((C16+F16)/1000,2) -> 1.67 | P16: =H16/1000 -> 1.62032 | Q16: =K16+L16*K16 -> 3719.8335
A17: Coal_10 | B17: 0.23013405 | C17: =(B17*10^7)/(8760*$B$1) -> 328.38763 | D17: 88076236 | E17: =D17*$B$4 -> 9703189.1 | F17: =(E17)/(8760*$B$1) -> 1384.5875 | G17: 0.37 | H17: =ROUND(('Coal Prices'!$C$11/'Coal Prices'!$H$5)/G17*(860000/1000),2) -> 1620.32 | I17: 0 | J17: 0 | K17: =C17+H17+F17 -> 3333.2951 | L17: 0.14 | M17: =C17+F17 -> 1712.9751 | O17: =ROUND((C17+F17)/1000,2) -> 1.71 | P17: =H17/1000 -> 1.62032 | Q17: =K17+L17*K17 -> 3799.9564
A18: Coal_11 | B18: 0.26014978 | C18: =(B18*10^7)/(8760*$B$1) -> 371.21829 | D18: 89228633 | E18: =D18*$B$4 -> 9830146.5 | F18: =(E18)/(8760*$B$1) -> 1402.7036 | G18: 0.36 | H18: =ROUND(('Coal Prices'!$C$11/'Coal Prices'!$H$5)/G18*(860000/1000),2) -> 1665.33 | I18: 0 | J18: 0 | K18: =C18+H18+F18 -> 3439.2518 | L18: 0.13 | M18: =C18+F18 -> 1773.9218 | O18: =ROUND((C18+F18)/1000,2) -> 1.77 | P18: =H18/1000 -> 1.66533 | Q18: =K18+L18*K18 -> 3886.3546
A19: Coal_12 | B19: 0.21160168 | C19: =(B19*10^7)/(8760*$B$1) -> 301.94304 | D19: 90239346 | E19: =D19*$B$4 -> 9941494.8 | F19: =(E19)/(8760*$B$1) -> 1418.5923 | G19: 0.36 | H19: =ROUND(('Coal Prices'!$C$11/'Coal Prices'!$H$5)/G19*(860000/1000),2) -> 1665.33 | I19: 0 | J19: 0 | K19: =C19+H19+F19 -> 3385.8653 | L19: 0.1 | M19: =C19+F19 -> 1720.5353 | O19: =ROUND((C19+F19)/1000,2) -> 1.72 | P19: =H19/1000 -> 1.66533 | Q19: =K19+L19*K19 -> 3724.4519
A20: Coal_13 | B20: 0.21050668 | C20: =(B20*10^7)/(8760*$B$1) -> 300.38053 | D20: 91244631 | E20: =D20*$B$4 -> 10052245 | F20: =(E20)/(8760*$B$1) -> 1434.3957 | G20: 0.36 | H20: =ROUND(('Coal Prices'!$C$11/'Coal Prices'!$H$5)/G20*(860000/1000),2) -> 1665.33 | I20: 0 | J20: 0 | K20: =C20+H20+F20 -> 3400.1062 | L20: 0.11 | M20: =C20+F20 -> 1734.7762 | O20: =ROUND((C20+F20)/1000,2) -> 1.73 | P20: =H20/1000 -> 1.66533 | Q20: =K20+L20*K20 -> 3774.1179
A21: Coal_14 | B21: 0.21645405 | C21: =(B21*10^7)/(8760*$B$1) -> 308.86708 | D21: 91309477 | E21: =D21*$B$4 -> 10059389 | F21: =(E21)/(8760*$B$1) -> 1435.4151 | G21: 0.35 | H21: =ROUND(('Coal Prices'!$C$11/'Coal Prices'!$H$5)/G21*(860000/1000),2) -> 1712.91 | I21: 0 | J21: 0 | K21: =C21+H21+F21 -> 3457.1922 | L21: 0.13 | M21: =C21+F21 -> 1744.2822 | O21: =ROUND((C21+F21)/1000,2) -> 1.74 | P21: =H21/1000 -> 1.71291 | Q21: =K21+L21*K21 -> 3906.6272
A22: Coal_15 | B22: 0.24784308 | C22: =(B22*10^7)/(8760*$B$1) -> 353.65736 | D22: 91982617 | E22: =D22*$B$4 -> 10133548 | F22: =(E22)/(8760*$B$1) -> 1445.9971 | G22: 0.32 | H22: =ROUND(('Coal Prices'!$C$11/'Coal Prices'!$H$5)/G22*(860000/1000),2) -> 1873.5 | I22: 0 | J22: 0 | K22: =C22+H22+F22 -> 3673.1544 | L22: 0.13 | M22: =C22+F22 -> 1799.6544 | O22: =ROUND((C22+F22)/1000,2) -> 1.8 | P22: =H22/1000 -> 1.8735 | Q22: =K22+L22*K22 -> 4150.6645
A24: Gas Turbine
A25: CCGTurbine_1 | B25: 0.18 | C25: =(B25*10^7)/(8760*$B$1) -> 256.84932 | D25: =5*10^7 -> 50000000 | E25: =D25*$B$4 -> 5508403.6 | F25: =(E25)/(8760*$B$1) -> 786.0165 | G25: 0.5 | H25: =ROUND(I25*'Gas Price'!$B$4/252/'Fixed cost calculation'!$G$25,2) -> 7263.06 | I25: 1375 | J25: 0 | K25: =C25+H25+F25 -> 8305.9258 | L25: 0.05 | M25: =C25+F25 -> 1042.8658 | O25: =ROUND((C25+F25)/1000,2) -> 1.04 | P25: =H25/1000 -> 7.26306 | Q25: =K25+L25*K25 -> 8721.2221
A26: Gas Turbine_2 | C26: =(B26*10^7)/(8760*$B$1) -> 0 | E26: =D26*$B$4 -> 0 | F26: =(E26)/(8760*$B$1) -> 0 | G26: =ROUND(RAND() * (0.45 - 0.28) + 0.28,2) -> 0.41 | H26: =ROUND(I26*'Gas Price'!$B$4/252/'Fixed cost calculation'!$G$25,2) -> 13406.28 | I26: 2538 | J26: 0 | K26: =C26+H26+F26 -> 13406.28 | L26: 0.05 | M26: =C26+F26 -> 0 | O26: =ROUND((C26+F26)/1000,2) -> 0 | P26: =H26/1000 -> 13.40628 | Q26: =K26+L26*K26 -> 14076.594
A27: Gas Turbine_3 | B27: 0.1 | C27: =(B27*10^7)/(8760*$B$1) -> 142.69406 | E27: =D27*$B$4 -> 0 | F27: =(E27)/(8760*$B$1) -> 0 | G27: =ROUND(RAND() * (0.45 - 0.28) + 0.28,2) -> 0.44 | H27: =ROUND(I27*'Gas Price'!$B$4/252/'Fixed cost calculation'!$G$25,2) -> 13474.95 | I27: 2551 | J27: 0 | K27: =C27+H27+F27 -> 13617.644 | L27: 0.05 | M27: =C27+F27 -> 142.69406 | O27: =ROUND((C27+F27)/1000,2) -> 0.14 | P27: =H27/1000 -> 13.47495 | Q27: =K27+L27*K27 -> 14298.526
A28: Gas Turbine_4 | C28: =(B28*10^7)/(8760*$B$1) -> 0 | E28: =D28*$B$4 -> 0 | F28: =(E28)/(8760*$B$1) -> 0 | G28: =ROUND(RAND() * (0.45 - 0.28) + 0.28,2) -> 0.36 | H28: =ROUND(I28*'Gas Price'!$B$4/252/'Fixed cost calculation'!$G$25,2) -> 10759.89 | I28: 2037 | J28: 0 | K28: =C28+H28+F28 -> 10759.89 | L28: 0.05 | M28: =C28+F28 -> 0 | O28: =ROUND((C28+F28)/1000,2) -> 0 | P28: =H28/1000 -> 10.75989 | Q28: =K28+L28*K28 -> 11297.885
A29: Gas Turbine_5 | C29: =(B29*10^7)/(8760*$B$1) -> 0 | E29: =D29*$B$4 -> 0 | F29: =(E29)/(8760*$B$1) -> 0 | G29: =ROUND(RAND() * (0.45 - 0.28) + 0.28,2) -> 0.44 | H29: =ROUND(I29*'Gas Price'!$B$4/252/'Fixed cost calculation'!$G$25,2) -> 14489.14 | I29: 2743 | J29: 0 | K29: =C29+H29+F29 -> 14489.14 | L29: 0.05 | M29: =C29+F29 -> 0 | O29: =ROUND((C29+F29)/1000,2) -> 0 | P29: =H29/1000 -> 14.48914 | Q29: =K29+L29*K29 -> 15213.597
A30: Gas Turbine_6 | B30: 0.371 | C30: =(B30*10^7)/(8760*$B$1) -> 529.39498 | E30: =D30*$B$4 -> 0 | F30: =(E30)/(8760*$B$1) -> 0 | G30: =ROUND(RAND() * (0.45 - 0.28) + 0.28,2) -> 0.32 | H30: =ROUND(I30*'Gas Price'!$B$4/252/'Fixed cost calculation'!$G$25,2) -> 14504.98 | I30: 2746 | J30: 0 | K30: =C30+H30+F30 -> 15034.375 | L30: 0.05 | M30: =C30+F30 -> 529.39498 | O30: =ROUND((C30+F30)/1000,2) -> 0.53 | P30: =H30/1000 -> 14.50498 | Q30: =K30+L30*K30 -> 15786.094
A31: Gas Turbine_7 | C31: =(B31*10^7)/(8760*$B$1) -> 0 | E31: =D31*$B$4 -> 0 | F31: =(E31)/(8760*$B$1) -> 0 | G31: =ROUND(RAND() * (0.45 - 0.28) + 0.28,2) -> 0.35 | H31: =ROUND(I31*'Gas Price'!$B$4/252/'Fixed cost calculation'!$G$25,2) -> 10601.42 | I31: 2007 | J31: 0 | K31: =C31+H31+F31 -> 10601.42 | L31: 0.05 | M31: =C31+F31 -> 0 | O31: =ROUND((C31+F31)/1000,2) -> 0 | P31: =H31/1000 -> 10.60142 | Q31: =K31+L31*K31 -> 11131.491
A32: Gas Turbine_8 | B32: 0.043 | C32: =(B32*10^7)/(8760*$B$1) -> 61.358447 | E32: =D32*$B$4 -> 0 | F32: =(E32)/(8760*$B$1) -> 0 | G32: =ROUND(RAND() * (0.45 - 0.28) + 0.28,2) -> 0.39 | H32: =ROUND(I32*'Gas Price'!$B$4/252/'Fixed cost calculation'!$G$25,2) -> 13797.16 | I32: 2612 | J32: 0 | K32: =C32+H32+F32 -> 13858.518 | L32: 0.05 | M32: =C32+F32 -> 61.358447 | O32: =ROUND((C32+F32)/1000,2) -> 0.06 | P32: =H32/1000 -> 13.79716 | Q32: =K32+L32*K32 -> 14551.444
A33: Gas Turbine_9 | C33: =(B33*10^7)/(8760*$B$1) -> 0 | E33: =D33*$B$4 -> 0 | F33: =(E33)/(8760*$B$1) -> 0 | G33: =ROUND(RAND() * (0.45 - 0.28) + 0.28,2) -> 0.4 | H33: =ROUND(I33*'Gas Price'!$B$4/252/'Fixed cost calculation'!$G$25,2) -> 15809.69 | I33: 2993 | J33: 0 | K33: =C33+H33+F33 -> 15809.69 | L33: 0.05 | M33: =C33+F33 -> 0 | O33: =ROUND((C33+F33)/1000,2) -> 0 | P33: =H33/1000 -> 15.80969 | Q33: =K33+L33*K33 -> 16600.175
A34: Gas Turbine_10 | B34: 0.15017451 | C34: =(B34*10^7)/(8760*$B$1) -> 214.29011 | D34: =RANDBETWEEN(4.1*10^7,5*10^7) -> 44790589 | E34: =D34*$B$4 -> 4934492.8 | F34: =(E34)/(8760*$B$1) -> 704.12284 | G34: 0.5 | H34: =ROUND(I34*'Gas Price'!$B$4/252/'Fixed cost calculation'!$G$25,2) -> 9867.19 | I34: 1868 | J34: 0 | K34: =C34+H34+F34 -> 10785.603 | L34: 0.05 | M34: =C34+F34 -> 918.41294 | O34: =ROUND((C34+F34)/1000,2) -> 0.92 | P34: =H34/1000 -> 9.86719 | Q34: =K34+L34*K34 -> 11324.883
A35: Gas Turbine_11 | B35: 0.10826235 | C35: =(B35*10^7)/(8760*$B$1) -> 154.48394 | D35: =RANDBETWEEN(4.1*10^7,5*10^7) -> 49066080 | E35: =D35*$B$4 -> 5405515.4 | F35: =(E35)/(8760*$B$1) -> 771.33497 | G35: 0.5 | H35: =ROUND(I35*'Gas Price'!$B$4/252/'Fixed cost calculation'!$G$25,2) -> 9867.19 | I35: 1868 | J35: 0 | K35: =C35+H35+F35 -> 10793.009 | L35: 0.05 | M35: =C35+F35 -> 925.81891 | O35: =ROUND((C35+F35)/1000,2) -> 0.93 | P35: =H35/1000 -> 9.86719 | Q35: =K35+L35*K35 -> 11332.659
A36: CCGTurbine_2 | B36: 0.08150416 | C36: =(B36*10^7)/(8760*$B$1) -> 116.3016 | D36: =RANDBETWEEN(4.1*10^7,4.5*10^7) -> 43592055 | E36: =D36*$B$4 -> 4802452.7 | F36: =(E36)/(8760*$B$1) -> 685.28149 | G36: 0.43 | H36: =ROUND(I36*'Gas Price'!$B$4/252/'Fixed cost calculation'!$G$25,2) -> 7368.7 | I36: 1395 | J36: 0 | K36: =C36+H36+F36 -> 8170.2831 | L36: 0.05 | M36: =C36+F36 -> 801.58308 | O36: =ROUND((C36+F36)/1000,2) -> 0.8 | P36: =H36/1000 -> 7.3687 | Q36: =K36+L36*K36 -> 8578.7972
A37: CCGTurbine_3 | B37: 0.05 | C37: =(B37*10^7)/(8760*$B$1) -> 71.347032 | D37: 40000000 | E37: =D37*$C$4 -> 4072250 | F37: =(E37)/(8760*$B$1) -> 581.0859 | G37: 0.38 | H37: =ROUND(I37*'Gas Price'!$B$4/252/'Fixed cost calculation'!$G$25,2) -> 6866.89 | I37: 1300 | J37: 0 | K37: =C37+H37+F37 -> 7519.3229 | L37: 0.02 | M37: =C37+F37 -> 652.43294 | O37: =ROUND((C37+F37)/1000,2) -> 0.65 | P37: =H37/1000 -> 6.86689 | Q37: =K37+L37*K37 -> 7669.7094
A38: CCGTurbine_4 | B38: 0.17273552 | C38: =(B38*10^7)/(8760*$B$1) -> 246.48333 | D38: =RANDBETWEEN(4.1*10^7,4.5*10^7) -> 42558513 | E38: =D38*$B$4 -> 4688589.3 | F38: =(E38)/(8760*$B$1) -> 669.03387 | G38: 0.41 | H38: =ROUND(I38*'Gas Price'!$B$4/252/'Fixed cost calculation'!$G$25,2) -> 8055.39 | I38: 1525 | J38: 0 | K38: =C38+H38+F38 -> 8970.9072 | L38: 0.05 | M38: =C38+F38 -> 915.51719 | O38: =ROUND((C38+F38)/1000,2) -> 0.92 | P38: =H38/1000 -> 8.05539 | Q38: =K38+L38*K38 -> 9419.4526
A39: CCGTurbine_5 | B39: 0.093666906 | C39: =(B39*10^7)/(8760*$B$1) -> 133.65711 | D39: =RANDBETWEEN(4.1*10^7,4.5*10^7) -> 41668407 | E39: =D39*$B$4 -> 4590528.1 | F39: =(E39)/(8760*$B$1) -> 655.04111 | G39: 0.34 | H39: =ROUND(I39*'Gas Price'!$B$4/252/'Fixed cost calculation'!$G$25,2) -> 7469.06 | I39: 1414 | J39: 0 | K39: =C39+H39+F39 -> 8257.7582 | L39: 0.05 | M39: =C39+F39 -> 788.69822 | O39: =ROUND((C39+F39)/1000,2) -> 0.79 | P39: =H39/1000 -> 7.46906 | Q39: =K39+L39*K39 -> 8670.6461
A40: CCGTurbine_6 | B40: 0.12882717 | C40: =(B40*10^7)/(8760*$B$1) -> 183.82873 | D40: =RANDBETWEEN(4.1*10^7,4.5*10^7) -> 41465230 | E40: =D40*$B$4 -> 4568144.5 | F40: =(E40)/(8760*$B$1) -> 651.8471 | G40: 0.39 | H40: =ROUND(I40*'Gas Price'!$B$4/252/'Fixed cost calculation'!$G$25,2) -> 7648.66 | I40: 1448 | J40: 0 | K40: =C40+H40+F40 -> 8484.3358 | L40: 0.05 | M40: =C40+F40 -> 835.67582 | O40: =ROUND((C40+F40)/1000,2) -> 0.84 | P40: =H40/1000 -> 7.64866 | Q40: =K40+L40*K40 -> 8908.5526
A41: CCGTurbine_8 | B41: 0.1374434 | C41: =(B41*10^7)/(8760*$B$1) -> 196.12357 | D41: =RANDBETWEEN(4.1*10^7,4.5*10^7) -> 44034368 | E41: =D41*$B$4 -> 4851181.4 | F41: =(E41)/(8760*$B$1) -> 692.23479 | G41: 0.3 | H41: =ROUND(I41*'Gas Price'!$B$4/252/'Fixed cost calculation'!$G$25,2) -> 8192.73 | I41: 1551 | J41: 0 | K41: =C41+H41+F41 -> 9081.0884 | L41: 0.05 | M41: =C41+F41 -> 888.35836 | O41: =ROUND((C41+F41)/1000,2) -> 0.89 | P41: =H41/1000 -> 8.19273 | Q41: =K41+L41*K41 -> 9535.1428
A42: CCGTurbine_9 | B42: 0.075158474 | C42: =(B42*10^7)/(8760*$B$1) -> 107.24668 | D42: =RANDBETWEEN(4.1*10^7,4.5*10^7) -> 44319181 | E42: =D42*$B$4 -> 4882558.7 | F42: =(E42)/(8760*$B$1) -> 696.71215 | G42: 0.42 | H42: =ROUND(I42*'Gas Price'!$B$4/252/'Fixed cost calculation'!$G$25,2) -> 8367.04 | I42: 1584 | J42: 0 | K42: =C42+H42+F42 -> 9170.9988 | L42: 0.05 | M42: =C42+F42 -> 803.95883 | O42: =ROUND((C42+F42)/1000,2) -> 0.8 | P42: =H42/1000 -> 8.36704 | Q42: =K42+L42*K42 -> 9629.5488
A43: CCGTurbine_10 | B43: 0.15800682 | C43: =(B43*10^7)/(8760*$B$1) -> 225.46636 | D43: =RANDBETWEEN(4.1*10^7,4.5*10^7) -> 41744310 | E43: =D43*$B$4 -> 4598890.2 | F43: =(E43)/(8760*$B$1) -> 656.23433 | G43: 0.29 | H43: =ROUND(I43*'Gas Price'!$B$4/252/'Fixed cost calculation'!$G$25,2) -> 7912.77 | I43: 1498 | J43: 0 | K43: =C43+H43+F43 -> 8794.4707 | L43: 0.05 | M43: =C43+F43 -> 881.70068 | O43: =ROUND((C43+F43)/1000,2) -> 0.88 | P43: =H43/1000 -> 7.91277 | Q43: =K43+L43*K43 -> 9234.1942
A44: Gas Turbine_20 | B44: 0.13254303 | C44: =(B44*10^7)/(8760*$B$1) -> 189.13103 | D44: =RANDBETWEEN(4.1*10^7,4.5*10^7) -> 41371106 | E44: =D44*$B$4 -> 4557775 | F44: =(E44)/(8760*$B$1) -> 650.36744 | G44: 0.35 | H44: =ROUND(I44*'Gas Price'!$B$4/252/'Fixed cost calculation'!$G$25,2) -> 7511.32 | I44: 1422 | J44: 0 | K44: =C44+H44+F44 -> 8350.8185 | L44: 0.05 | M44: =C44+F44 -> 839.49847 | O44: =ROUND((C44+F44)/1000,2) -> 0.84 | P44: =H44/1000 -> 7.51132 | Q44: =K44+L44*K44 -> 8768.3594
A50: Hydro
A51: Hydro_1 | B51: 0.375 | C51: =(B51*10^7)/(8760*$B$1) -> 535.10274 | D51: =10.7*10^7 -> 107000000 | E51: =D51*$B$4 -> 11787984 | F51: =(E51)/(8760*$B$1) -> 1682.0753 | G51: 0.37 | H51: 0 | I51: 0 | J51: 0 | K51: =C51+H51+F51 -> 2217.178 | L51: 0.15 | M51: =C51+F51 -> 2217.178 | O51: =ROUND((C51+F51)/1000,2) -> 2.22 | P51: =H51/1000 -> 0 | Q51: =K51+L51*K51 -> 2549.7547
A52: Hydro_2 | B52: 0.17037915 | C52: =(B52*10^7)/(8760*$B$1) -> 243.12093 | D52: =RANDBETWEEN(5*10^7,11*10^7) -> 53220694 | E52: =D52*$B$4 -> 5863221.3 | F52: =(E52)/(8760*$B$1) -> 836.64687 | G52: 0.28 | H52: 0 | I52: 0 | J52: 0 | K52: =C52+H52+F52 -> 1079.7678 | L52: 0.19 | M52: =C52+F52 -> 1079.7678 | O52: =ROUND((C52+F52)/1000,2) -> 1.08 | P52: =H52/1000 -> 0 | Q52: =K52+L52*K52 -> 1284.9237
A53: Hydro_3 | B53: 0.42324057 | C53: =(B53*10^7)/(8760*$B$1) -> 603.93917 | D53: =RANDBETWEEN(5*10^7,11*10^7) -> 84670887 | E53: =D53*$B$4 -> 9328028.4 | F53: =(E53)/(8760*$B$1) -> 1331.0543 | G53: 0.36 | H53: 0 | I53: 0 | J53: 0 | K53: =C53+H53+F53 -> 1934.9935 | L53: 0.12 | M53: =C53+F53 -> 1934.9935 | O53: =ROUND((C53+F53)/1000,2) -> 1.93 | P53: =H53/1000 -> 0 | Q53: =K53+L53*K53 -> 2167.1927
A54: Hydro_4 | B54: 0.39397173 | C54: =(B54*10^7)/(8760*$B$1) -> 562.17427 | D54: =RANDBETWEEN(5*10^7,11*10^7) -> 109298688 | E54: =D54*$B$4 -> 12041226 | F54: =(E54)/(8760*$B$1) -> 1718.2114 | G54: 0.33 | H54: 0 | I54: 0 | J54: 0 | K54: =C54+H54+F54 -> 2280.3857 | L54: 0.11 | M54: =C54+F54 -> 2280.3857 | O54: =ROUND((C54+F54)/1000,2) -> 2.28 | P54: =H54/1000 -> 0 | Q54: =K54+L54*K54 -> 2531.2281
A55: Hydro_5 | B55: 0.28080302 | C55: =(B55*10^7)/(8760*$B$1) -> 400.68924 | D55: =RANDBETWEEN(5*10^7,11*10^7) -> 59220906 | E55: =D55*$B$4 -> 6524253 | F55: =(E55)/(8760*$B$1) -> 930.97218 | G55: 0.28 | H55: 0 | I55: 0 | J55: 0 | K55: =C55+H55+F55 -> 1331.6614 | L55: 0.25 | M55: =C55+F55 -> 1331.6614 | O55: =ROUND((C55+F55)/1000,2) -> 1.33 | P55: =H55/1000 -> 0 | Q55: =K55+L55*K55 -> 1664.5768
A56: Hydro_6 | B56: 0.24454679 | C56: =(B56*10^7)/(8760*$B$1) -> 348.95375 | D56: =RANDBETWEEN(5*10^7,11*10^7) -> 83139774 | E56: =D56*$B$4 -> 9159348.6 | F56: =(E56)/(8760*$B$1) -> 1306.9847 | G56: 0.28 | H56: 0 | I56: 0 | J56: 0 | K56: =C56+H56+F56 -> 1655.9384 | L56: 0.22 | M56: =C56+F56 -> 1655.9384 | O56: =ROUND((C56+F56)/1000,2) -> 1.66 | P56: =H56/1000 -> 0 | Q56: =K56+L56*K56 -> 2020.2449
A57: Hydro_7 | B57: 0.32705936 | C57: =(B57*10^7)/(8760*$B$1) -> 466.69429 | D57: =RANDBETWEEN(5*10^7,11*10^7) -> 83330503 | E57: =D57*$B$4 -> 9180360.9 | F57: =(E57)/(8760*$B$1) -> 1309.983 | G57: 0.4 | H57: 0 | I57: 0 | J57: 0 | K57: =C57+H57+F57 -> 1776.6773 | L57: 0.1 | M57: =C57+F57 -> 1776.6773 | O57: =ROUND((C57+F57)/1000,2) -> 1.78 | P57: =H57/1000 -> 0 | Q57: =K57+L57*K57 -> 1954.345
A58: Hydro_8 | B58: 0.24682894 | C58: =(B58*10^7)/(8760*$B$1) -> 352.21025 | D58: =RANDBETWEEN(5*10^7,11*10^7) -> 97560457 | E58: =D58*$B$4 -> 10748047 | F58: =(E58)/(8760*$B$1) -> 1533.6826 | G58: 0.31 | H58: 0 | I58: 0 | J58: 0 | K58: =C58+H58+F58 -> 1885.8928 | L58: 0.12 | M58: =C58+F58 -> 1885.8928 | O58: =ROUND((C58+F58)/1000,2) -> 1.89 | P58: =H58/1000 -> 0 | Q58: =K58+L58*K58 -> 2112.2
A59: Hydro_9 | B59: 0.41489482 | C59: =(B59*10^7)/(8760*$B$1) -> 592.03029 | D59: =RANDBETWEEN(5*10^7,11*10^7) -> 55424804 | E59: =D59*$B$4 -> 6106043.8 | F59: =(E59)/(8760*$B$1) -> 871.29621 | G59: 0.4 | H59: 0 | I59: 0 | J59: 0 | K59: =C59+H59+F59 -> 1463.3265 | L59: 0.21 | M59: =C59+F59 -> 1463.3265 | O59: =ROUND((C59+F59)/1000,2) -> 1.46 | P59: =H59/1000 -> 0 | Q59: =K59+L59*K59 -> 1770.6251
A60: Hydro_10 | B60: 0.29237049 | C60: =(B60*10^7)/(8760*$B$1) -> 417.19534 | D60: =RANDBETWEEN(5*10^7,11*10^7) -> 55735231 | E60: =D60*$B$4 -> 6140243 | F60: =(E60)/(8760*$B$1) -> 876.17622 | G60: 0.35 | H60: 0 | I60: 0 | J60: 0 | K60: =C60+H60+F60 -> 1293.3716 | L60: 0.18 | M60: =C60+F60 -> 1293.3716 | O60: =ROUND((C60+F60)/1000,2) -> 1.29 | P60: =H60/1000 -> 0 | Q60: =K60+L60*K60 -> 1526.1784
A61: Hydro_11 | B61: 0.14871977 | C61: =(B61*10^7)/(8760*$B$1) -> 212.21428 | D61: =RANDBETWEEN(5*10^7,11*10^7) -> 93687719 | E61: =D61*$B$4 -> 10321395 | F61: =(E61)/(8760*$B$1) -> 1472.8019 | G61: 0.44 | H61: 0 | I61: 0 | J61: 0 | K61: =C61+H61+F61 -> 1685.0161 | L61: 0.25 | M61: =C61+F61 -> 1685.0161 | O61: =ROUND((C61+F61)/1000,2) -> 1.69 | P61: =H61/1000 -> 0 | Q61: =K61+L61*K61 -> 2106.2702
A62: Hydro_12 | B62: 0.42532295 | C62: =(B62*10^7)/(8760*$B$1) -> 606.91061 | D62: =RANDBETWEEN(5*10^7,11*10^7) -> 88968493 | E62: =D62*$B$4 -> 9801487.4 | F62: =(E62)/(8760*$B$1) -> 1398.6141 | G62: 0.31 | H62: 0 | I62: 0 | J62: 0 | K62: =C62+H62+F62 -> 2005.5247 | L62: 0.11 | M62: =C62+F62 -> 2005.5247 | O62: =ROUND((C62+F62)/1000,2) -> 2.01 | P62: =H62/1000 -> 0 | Q62: =K62+L62*K62 -> 2226.1324
A63: Hydro_13 | B63: 0.12670334 | C63: =(B63*10^7)/(8760*$B$1) -> 180.79815 | D63: =RANDBETWEEN(5*10^7,11*10^7) -> 62647070 | E63: =D63*$B$4 -> 6901706.9 | F63: =(E63)/(8760*$B$1) -> 984.83261 | G63: 0.44 | H63: 0 | I63: 0 | J63: 0 | K63: =C63+H63+F63 -> 1165.6308 | L63: 0.11 | M63: =C63+F63 -> 1165.6308 | O63: =ROUND((C63+F63)/1000,2) -> 1.17 | P63: =H63/1000 -> 0 | Q63: =K63+L63*K63 -> 1293.8501
A64: Hydro_14 | B64: 0.18245981 | C64: =(B64*10^7)/(8760*$B$1) -> 260.35932 | D64: =RANDBETWEEN(5*10^7,11*10^7) -> 74866321 | E64: =D64*$B$4 -> 8247878.3 | F64: =(E64)/(8760*$B$1) -> 1176.9233 | G64: 0.44 | H64: 0 | I64: 0 | J64: 0 | K64: =C64+H64+F64 -> 1437.2826 | L64: 0.12 | M64: =C64+F64 -> 1437.2826 | O64: =ROUND((C64+F64)/1000,2) -> 1.44 | P64: =H64/1000 -> 0 | Q64: =K64+L64*K64 -> 1609.7565
A66: Solar
A67: Solar_1 | B67: 0.035 | C67: =(B67*10^7)/(8760*$B$1) -> 49.942922 | D67: =5.4*10^7 -> 54000000 | E67: =D67*$B$4 -> 5949075.9 | F67: =(E67)/(8760*$B$1) -> 848.89782 | G67: 0.42 | H67: 0 | I67: 0 | J67: 0 | K67: =C67+H67+F67 -> 898.84074 | L67: 0.12 | M67: =C67+F67 -> 898.84074 | O67: =ROUND((C67+F67)/1000,2) -> 0.9 | P67: =H67/1000 -> 0 | Q67: =K67+L67*K67 -> 1006.7016
A68: Solar_2 | B68: 0.21010743 | C68: =(B68*10^7)/(8760*$B$1) -> 299.81083 | D68: =RANDBETWEEN(5*10^7,6*10^7) -> 57409553 | E68: =D68*$B$4 -> 6324699.8 | F68: =(E68)/(8760*$B$1) -> 902.49711 | G68: 0.3 | H68: 0 | I68: 0 | J68: 0 | K68: =C68+H68+F68 -> 1202.3079 | L68: 0.18 | M68: =C68+F68 -> 1202.3079 | O68: =ROUND((C68+F68)/1000,2) -> 1.2 | P68: =H68/1000 -> 0 | Q68: =K68+L68*K68 -> 1418.7234
A69: Solar_3 | B69: 0.038230202 | C69: =(B69*10^7)/(8760*$B$1) -> 54.552229 | D69: =RANDBETWEEN(5*10^7,6*10^7) -> 56235702 | E69: =D69*$B$4 -> 6195378.9 | F69: =(E69)/(8760*$B$1) -> 884.04379 | G69: 0.34 | H69: 0 | I69: 0 | J69: 0 | K69: =C69+H69+F69 -> 938.59602 | L69: 0.15 | M69: =C69+F69 -> 938.59602 | O69: =ROUND((C69+F69)/1000,2) -> 0.94 | P69: =H69/1000 -> 0 | Q69: =K69+L69*K69 -> 1079.3854
A70: Solar_4 | B70: 0.037948649 | C70: =(B70*10^7)/(8760*$B$1) -> 54.150469 | D70: =RANDBETWEEN(5*10^7,6*10^7) -> 58921626 | E70: =D70*$B$4 -> 6491281.9 | F70: =(E70)/(8760*$B$1) -> 926.2674 | G70: 0.42 | H70: 0 | I70: 0 | J70: 0 | K70: =C70+H70+F70 -> 980.41787 | L70: 0.13 | M70: =C70+F70 -> 980.41787 | O70: =ROUND((C70+F70)/1000,2) -> 0.98 | P70: =H70/1000 -> 0 | Q70: =K70+L70*K70 -> 1107.8722
A71: Solar_5 | B71: 0.031543168 | C71: =(B71*10^7)/(8760*$B$1) -> 45.010228 | D71: =RANDBETWEEN(5*10^7,6*10^7) -> 57419936 | E71: =D71*$B$4 -> 6325843.7 | F71: =(E71)/(8760*$B$1) -> 902.66034 | G71: 0.32 | H71: 0 | I71: 0 | J71: 0 | K71: =C71+H71+F71 -> 947.67057 | L71: 0.12 | M71: =C71+F71 -> 947.67057 | O71: =ROUND((C71+F71)/1000,2) -> 0.95 | P71: =H71/1000 -> 0 | Q71: =K71+L71*K71 -> 1061.391
A72: Solar_6 | B72: 0.031607898 | C72: =(B72*10^7)/(8760*$B$1) -> 45.102594 | D72: =RANDBETWEEN(5*10^7,6*10^7) -> 57587927 | E72: =D72*$B$4 -> 6344350.9 | F72: =(E72)/(8760*$B$1) -> 905.30121 | G72: 0.41 | H72: 0 | I72: 0 | J72: 0 | K72: =C72+H72+F72 -> 950.40381 | L72: 0.23 | M72: =C72+F72 -> 950.40381 | O72: =ROUND((C72+F72)/1000,2) -> 0.95 | P72: =H72/1000 -> 0 | Q72: =K72+L72*K72 -> 1168.9967
A73: Solar_7 | B73: 0.030124271 | C73: =(B73*10^7)/(8760*$B$1) -> 42.985546 | D73: =RANDBETWEEN(5*10^7,6*10^7) -> 57504813 | E73: =D73*$B$4 -> 6335194.4 | F73: =(E73)/(8760*$B$1) -> 903.99463 | G73: 0.41 | H73: 0 | I73: 0 | J73: 0 | K73: =C73+H73+F73 -> 946.98018 | L73: 0.19 | M73: =C73+F73 -> 946.98018 | O73: =ROUND((C73+F73)/1000,2) -> 0.95 | P73: =H73/1000 -> 0 | Q73: =K73+L73*K73 -> 1126.9064
A74: Solar_8 | B74: 0.035647621 | C74: =(B74*10^7)/(8760*$B$1) -> 50.86704 | D74: =RANDBETWEEN(5*10^7,6*10^7) -> 51390691 | E74: =D74*$B$4 -> 5661613.4 | F74: =(E74)/(8760*$B$1) -> 807.87862 | G74: 0.38 | H74: 0 | I74: 0 | J74: 0 | K74: =C74+H74+F74 -> 858.74566 | L74: 0.12 | M74: =C74+F74 -> 858.74566 | O74: =ROUND((C74+F74)/1000,2) -> 0.86 | P74: =H74/1000 -> 0 | Q74: =K74+L74*K74 -> 961.79514
A75: Solar_9 | B75: 0.031388387 | C75: =(B75*10^7)/(8760*$B$1) -> 44.789365 | D75: =RANDBETWEEN(5*10^7,6*10^7) -> 58525518 | E75: =D75*$B$4 -> 6447643.5 | F75: =(E75)/(8760*$B$1) -> 920.04045 | G75: 0.36 | H75: 0 | I75: 0 | J75: 0 | K75: =C75+H75+F75 -> 964.82982 | L75: 0.23 | M75: =C75+F75 -> 964.82982 | O75: =ROUND((C75+F75)/1000,2) -> 0.96 | P75: =H75/1000 -> 0 | Q75: =K75+L75*K75 -> 1186.7407
A76: Solar_10 | B76: 0.034479437 | C76: =(B76*10^7)/(8760*$B$1) -> 49.200109 | D76: =RANDBETWEEN(5*10^7,6*10^7) -> 50314803 | E76: =D76*$B$4 -> 5543084.8 | F76: =(E76)/(8760*$B$1) -> 790.9653 | G76: 0.34 | H76: 0 | I76: 0 | J76: 0 | K76: =C76+H76+F76 -> 840.16541 | L76: 0.21 | M76: =C76+F76 -> 840.16541 | O76: =ROUND((C76+F76)/1000,2) -> 0.84 | P76: =H76/1000 -> 0 | Q76: =K76+L76*K76 -> 1016.6001
A77: Solar_11 | B77: 0.039758888 | C77: =(B77*10^7)/(8760*$B$1) -> 56.733573 | D77: =RANDBETWEEN(5*10^7,6*10^7) -> 58441389 | E77: =D77*$B$4 -> 6438375.2 | F77: =(E77)/(8760*$B$1) -> 918.71792 | G77: 0.33 | H77: 0 | I77: 0 | J77: 0 | K77: =C77+H77+F77 -> 975.45149 | L77: 0.15 | M77: =C77+F77 -> 975.45149 | O77: =ROUND((C77+F77)/1000,2) -> 0.98 | P77: =H77/1000 -> 0 | Q77: =K77+L77*K77 -> 1121.7692
A78: Solar_12 | B78: 0.039342227 | C78: =(B78*10^7)/(8760*$B$1) -> 56.139022 | D78: =RANDBETWEEN(5*10^7,6*10^7) -> 52535092 | E78: =D78*$B$4 -> 5787689.8 | F78: =(E78)/(8760*$B$1) -> 825.86898 | G78: 0.4 | H78: 0 | I78: 0 | J78: 0 | K78: =C78+H78+F78 -> 882.008 | L78: 0.17 | M78: =C78+F78 -> 882.008 | O78: =ROUND((C78+F78)/1000,2) -> 0.88 | P78: =H78/1000 -> 0 | Q78: =K78+L78*K78 -> 1031.9494
A79: Solar_13 | B79: 0.030964487 | C79: =(B79*10^7)/(8760*$B$1) -> 44.184485 | D79: =RANDBETWEEN(5*10^7,6*10^7) -> 56032076 | E79: =D79*$B$4 -> 6172945.8 | F79: =(E79)/(8760*$B$1) -> 880.84272 | G79: 0.44 | H79: 0 | I79: 0 | J79: 0 | K79: =C79+H79+F79 -> 925.02721 | L79: 0.2 | M79: =C79+F79 -> 925.02721 | O79: =ROUND((C79+F79)/1000,2) -> 0.93 | P79: =H79/1000 -> 0 | Q79: =K79+L79*K79 -> 1110.0326
... A95: Solar_29 | B95: 0.036852848 | C95: =(B95*10^7)/(8760*$B$1) -> 52.586827 | D95: =RANDBETWEEN(5*10^7,6*10^7) -> 55084179 | E95: =D95*$B$4 -> 6068517.8 | F95: =(E95)/(8760*$B$1) -> 865.94147 | G95: 0.35 | H95: 0 | I95: 0 | J95: 0 | K95: =C95+H95+F95 -> 918.52829 | L95: 0.17 | M95: =C95+F95 -> 918.52829 | O95: =ROUND((C95+F95)/1000,2) -> 0.92 | P95: =H95/1000 -> 0 | Q95: =K95+L95*K95 -> 1074.6781
A97: Nuclear
A98: Nuclear_1 | B98: 0.345 | C98: =(B98*10^7)/(8760*$B$1) -> 492.29452 | D98: =19*10^7 -> 190000000 | E98: =D98*$B$4 -> 20931934 | F98: =(E98)/(8760*$B$1) -> 2986.8627 | G98: 0.45 | H98: 0 | I98: 0 | J98: 0 | K98: =C98+H98+F98 -> 3479.1572 | L98: 0.22 | M98: =C98+F98 -> 3479.1572 | O98: =ROUND((C98+F98)/1000,2) -> 3.48 | P98: =H98/1000 -> 0 | Q98: =K98+L98*K98 -> 4244.5718
A99: Nuclear_2 | B99: 0.38222713 | C99: =(B99*10^7)/(8760*$B$1) -> 545.41543 | D99: =RANDBETWEEN(11.7*10^7,19*10^7) -> 174216961 | E99: =D99*$B$4 -> 19193147 | F99: =(E99)/(8760*$B$1) -> 2738.7481 | G99: 0.35 | H99: =RANDBETWEEN(650,800) -> 775 | I99: 0 | J99: 0 | K99: =C99+H99+F99 -> 4059.1635 | L99: 0.11 | M99: =C99+F99 -> 3284.1635 | O99: =ROUND((C99+F99)/1000,2) -> 3.28 | P99: =H99/1000 -> 0.775 | Q99: =K99+L99*K99 -> 4505.6715
A100: Nuclear_3 | B100: 0.36007642 | C100: =(B100*10^7)/(8760*$B$1) -> 513.80768 | D100: =RANDBETWEEN(11.7*10^7,19*10^7) -> 165862751 | E100: =D100*$B$4 -> 18272780 | F100: =(E100)/(8760*$B$1) -> 2607.4172 | G100: 0.33 | H100: =RANDBETWEEN(650,800) -> 739 | I100: 0 | J100: 0 | K100: =C100+H100+F100 -> 3860.2249 | L100: 0.21 | M100: =C100+F100 -> 3121.2249 | O100: =ROUND((C100+F100)/1000,2) -> 3.12 | P100: =H100/1000 -> 0.739 | Q100: =K100+L100*K100 -> 4670.8721
A101: Nuclear_4 | B101: 0.31346955 | C101: =(B101*10^7)/(8760*$B$1) -> 447.30244 | D101: =RANDBETWEEN(11.7*10^7,19*10^7) -> 167145072 | E101: =D101*$B$4 -> 18414050 | F101: =(E101)/(8760*$B$1) -> 2627.5757 | G101: 0.38 | H101: =RANDBETWEEN(650,800) -> 786 | I101: 0 | J101: 0 | K101: =C101+H101+F101 -> 3860.8781 | L101: 0.12 | M101: =C101+F101 -> 3074.8781 | O101: =ROUND((C101+F101)/1000,2) -> 3.07 | P101: =H101/1000 -> 0.786 | Q101: =K101+L101*K101 -> 4324.1835
A102: Nuclear_5 | B102: 0.26824494 | C102: =(B102*10^7)/(8760*$B$1) -> 382.7696 | D102: =RANDBETWEEN(11.7*10^7,19*10^7) -> 137287622 | E102: =D102*$B$4 -> 15124713 | F102: =(E102)/(8760*$B$1) -> 2158.2067 | G102: 0.43 | H102: =RANDBETWEEN(650,800) -> 789 | I102: 0 | J102: 0 | K102: =C102+H102+F102 -> 3329.9763 | L102: 0.15 | M102: =C102+F102 -> 2540.9763 | O102: =ROUND((C102+F102)/1000,2) -> 2.54 | P102: =H102/1000 -> 0.789 | Q102: =K102+L102*K102 -> 3829.4728
A103: Nuclear_6 | B103: 0.29065877 | C103: =(B103*10^7)/(8760*$B$1) -> 414.75281 | D103: =RANDBETWEEN(11.7*10^7,19*10^7) -> 178032778 | E103: =D103*$B$4 -> 19613528 | F103: =(E103)/(8760*$B$1) -> 2798.734 | G103: 0.45 | H103: =RANDBETWEEN(650,800) -> 771 | I103: 0 | J103: 0 | K103: =C103+H103+F103 -> 3984.4868 | L103: 0.18 | M103: =C103+F103 -> 3213.4868 | O103: =ROUND((C103+F103)/1000,2) -> 3.21 | P103: =H103/1000 -> 0.771 | Q103: =K103+L103*K103 -> 4701.6945
A104: Nuclear_7 | B104: 0.30116136 | C104: =(B104*10^7)/(8760*$B$1) -> 429.73938 | D104: =RANDBETWEEN(11.7*10^7,19*10^7) -> 173512936 | E104: =D104*$B$4 -> 19115586 | F104: =(E104)/(8760*$B$1) -> 2727.6806 | G104: 0.33 | H104: =RANDBETWEEN(650,800) -> 729 | I104: 0 | J104: 0 | K104: =C104+H104+F104 -> 3886.42 | L104: 0.13 | M104: =C104+F104 -> 3157.42 | O104: =ROUND((C104+F104)/1000,2) -> 3.16 | P104: =H104/1000 -> 0.729 | Q104: =K104+L104*K104 -> 4391.6546
A105: Nuclear_8 | B105: 0.41539147 | C105: =(B105*10^7)/(8760*$B$1) -> 592.73896 | D105: =RANDBETWEEN(11.7*10^7,19*10^7) -> 129931440 | E105: =D105*$B$4 -> 14314296 | F105: =(E105)/(8760*$B$1) -> 2042.5651 | G105: 0.39 | H105: =RANDBETWEEN(650,800) -> 789 | I105: 0 | J105: 0 | K105: =C105+H105+F105 -> 3424.3041 | L105: 0.19 | M105: =C105+F105 -> 2635.3041 | O105: =ROUND((C105+F105)/1000,2) -> 2.64 | P105: =H105/1000 -> 0.789 | Q105: =K105+L105*K105 -> 4074.9218
A106: Nuclear_9 | B106: 0.39113641 | C106: =(B106*10^7)/(8760*$B$1) -> 558.12844 | D106: =RANDBETWEEN(11.7*10^7,19*10^7) -> 134267236 | E106: =D106*$B$4 -> 14791963 | F106: =(E106)/(8760*$B$1) -> 2110.7252 | G106: 0.41 | H106: =RANDBETWEEN(650,800) -> 727 | I106: 0 | J106: 0 | K106: =C106+H106+F106 -> 3395.8537 | L106: 0.16 | M106: =C106+F106 -> 2668.8537 | O106: =ROUND((C106+F106)/1000,2) -> 2.67 | P106: =H106/1000 -> 0.727 | Q106: =K106+L106*K106 -> 3939.1903
A107: Nuclear_10 | B107: 0.42504114 | C107: =(B107*10^7)/(8760*$B$1) -> 606.50848 | D107: =RANDBETWEEN(11.7*10^7,19*10^7) -> 148237853 | E107: =D107*$B$4 -> 16331078 | F107: =(E107)/(8760*$B$1) -> 2330.348 | G107: 0.38 | H107: =RANDBETWEEN(650,800) -> 779 | I107: 0 | J107: 0 | K107: =C107+H107+F107 -> 3715.8564 | L107: 0.22 | M107: =C107+F107 -> 2936.8564 | O107: =ROUND((C107+F107)/1000,2) -> 2.94 | P107: =H107/1000 -> 0.779 | Q107: =K107+L107*K107 -> 4533.3449
A108: Nuclear_11 | B108: 0.32221784 | C108: =(B108*10^7)/(8760*$B$1) -> 459.78573 | D108: =RANDBETWEEN(11.7*10^7,19*10^7) -> 146699487 | E108: =D108*$B$4 -> 16161600 | F108: =(E108)/(8760*$B$1) -> 2306.1643 | G108: 0.39 | H108: =RANDBETWEEN(650,800) -> 739 | I108: 0 | J108: 0 | K108: =C108+H108+F108 -> 3504.9501 | L108: 0.12 | M108: =C108+F108 -> 2765.9501 | O108: =ROUND((C108+F108)/1000,2) -> 2.77 | P108: =H108/1000 -> 0.739 | Q108: =K108+L108*K108 -> 3925.5441
A109: Nuclear_12 | B109: 0.37556379 | C109: =(B109*10^7)/(8760*$B$1) -> 535.90723 | D109: =RANDBETWEEN(11.7*10^7,19*10^7) -> 132950025 | E109: =D109*$B$4 -> 14646848 | F109: =(E109)/(8760*$B$1) -> 2090.0183 | G109: 0.39 | H109: =RANDBETWEEN(650,800) -> 668 | I109: 0 | J109: 0 | K109: =C109+H109+F109 -> 3293.9255 | L109: 0.24 | M109: =C109+F109 -> 2625.9255 | O109: =ROUND((C109+F109)/1000,2) -> 2.63 | P109: =H109/1000 -> 0.668 | Q109: =K109+L109*K109 -> 4084.4676
A111: Wind
A112: Wind_1 | B112: 0.068 | C112: =(B112*10^7)/(8760*$B$1) -> 97.031963 | D112: =6.66*10^7 -> 66600000 | E112: =D112*$B$4 -> 7337193.6 | F112: =(E112)/(8760*$B$1) -> 1046.974 | G112: 0.37 | H112: 0 | I112: 0 | J112: 0 | K112: =C112+H112+F112 -> 1144.0059 | L112: 0.13 | M112: =C112+F112 -> 1144.0059 | O112: =ROUND((C112+F112)/1000,2) -> 1.14 | P112: =H112/1000 -> 0 | Q112: =K112+L112*K112 -> 1292.7267
A113: Wind_2 | B113: 0.65445295 | C113: =(B113*10^7)/(8760*$B$1) -> 933.86551 | D113: =RANDBETWEEN(2*10^7,8*10^7) -> 29820401 | E113: =D113*$B$4 -> 3285256.1 | F113: =(E113)/(8760*$B$1) -> 468.78654 | G113: 0.33 | H113: 0 | I113: 0 | J113: 0 | K113: =C113+H113+F113 -> 1402.652 | L113: 0.19 | M113: =C113+F113 -> 1402.652 | O113: =ROUND((C113+F113)/1000,2) -> 1.4 | P113: =H113/1000 -> 0 | Q113: =K113+L113*K113 -> 1669.1559
A114: Wind_3 | B114: 0.484252 | C114: =(B114*10^7)/(8760*$B$1) -> 690.99886 | D114: =RANDBETWEEN(2*10^7,8*10^7) -> 41402897 | E114: =D114*$B$4 -> 4561277.3 | F114: =(E114)/(8760*$B$1) -> 650.8672 | G114: 0.39 | H114: 0 | I114: 0 | J114: 0 | K114: =C114+H114+F114 -> 1341.8661 | L114: 0.21 | M114: =C114+F114 -> 1341.8661 | O114: =ROUND((C114+F114)/1000,2) -> 1.34 | P114: =H114/1000 -> 0 | Q114: =K114+L114*K114 -> 1623.6579
A115: Wind_4 | B115: 0.064325073 | C115: =(B115*10^7)/(8760*$B$1) -> 91.78806 | D115: =RANDBETWEEN(2*10^7,8*10^7) -> 67363865 | E115: =D115*$B$4 -> 7421347.1 | F115: =(E115)/(8760*$B$1) -> 1058.9822 | G115: 0.4 | H115: 0 | I115: 0 | J115: 0 | K115: =C115+H115+F115 -> 1150.7702 | L115: 0.19 | M115: =C115+F115 -> 1150.7702 | O115: =ROUND((C115+F115)/1000,2) -> 1.15 | P115: =H115/1000 -> 0 | Q115: =K115+L115*K115 -> 1369.4166
A116: Wind_5 | B116: 0.58155423 | C116: =(B116*10^7)/(8760*$B$1) -> 829.84336 | D116: =RANDBETWEEN(2*10^7,8*10^7) -> 62241488 | E116: =D116*$B$4 -> 6857024.7 | F116: =(E116)/(8760*$B$1) -> 978.45673 | G116: 0.32 | H116: 0 | I116: 0 | J116: 0 | K116: =C116+H116+F116 -> 1808.3001 | L116: 0.15 | M116: =C116+F116 -> 1808.3001 | O116: =ROUND((C116+F116)/1000,2) -> 1.81 | P116: =H116/1000 -> 0 | Q116: =K116+L116*K116 -> 2079.5451
A117: Wind_6 | B117: 0.54434773 | C117: =(B117*10^7)/(8760*$B$1) -> 776.7519 | D117: =RANDBETWEEN(2*10^7,8*10^7) -> 29691305 | E117: =D117*$B$4 -> 3271033.8 | F117: =(E117)/(8760*$B$1) -> 466.75711 | G117: 0.29 | H117: 0 | I117: 0 | J117: 0 | K117: =C117+H117+F117 -> 1243.509 | L117: 0.15 | M117: =C117+F117 -> 1243.509 | O117: =ROUND((C117+F117)/1000,2) -> 1.24 | P117: =H117/1000 -> 0 | Q117: =K117+L117*K117 -> 1430.0354
A118: Wind_7 | B118: 0.069350205 | C118: =(B118*10^7)/(8760*$B$1) -> 98.958626 | D118: =RANDBETWEEN(2*10^7,8*10^7) -> 47666461 | E118: =D118*$B$4 -> 5251322.1 | F118: =(E118)/(8760*$B$1) -> 749.33249 | G118: 0.44 | H118: 0 | I118: 0 | J118: 0 | K118: =C118+H118+F118 -> 848.29112 | L118: 0.24 | M118: =C118+F118 -> 848.29112 | O118: =ROUND((C118+F118)/1000,2) -> 0.85 | P118: =H118/1000 -> 0 | Q118: =K118+L118*K118 -> 1051.881
A119: Wind_8 | B119: 0.39378035 | C119: =(B119*10^7)/(8760*$B$1) -> 561.90119 | D119: =RANDBETWEEN(2*10^7,8*10^7) -> 65181272 | E119: =D119*$B$4 -> 7180895.1 | F119: =(E119)/(8760*$B$1) -> 1024.6711 | G119: 0.4 | H119: 0 | I119: 0 | J119: 0 | K119: =C119+H119+F119 -> 1586.5723 | L119: 0.24 | M119: =C119+F119 -> 1586.5723 | O119: =ROUND((C119+F119)/1000,2) -> 1.59 | P119: =H119/1000 -> 0 | Q119: =K119+L119*K119 -> 1967.3496
A120: Wind_9 | B120: 0.5270092 | C120: =(B120*10^7)/(8760*$B$1) -> 752.01085 | D120: =RANDBETWEEN(2*10^7,8*10^7) -> 38454091 | E120: =D120*$B$4 -> 4236413.1 | F120: =(E120)/(8760*$B$1) -> 604.511 | G120: 0.44 | H120: 0 | I120: 0 | J120: 0 | K120: =C120+H120+F120 -> 1356.5218 | L120: 0.22 | M120: =C120+F120 -> 1356.5218 | O120: =ROUND((C120+F120)/1000,2) -> 1.36 | P120: =H120/1000 -> 0 | Q120: =K120+L120*K120 -> 1654.9567
A121: Wind_10 | B121: 0.16260191 | C121: =(B121*10^7)/(8760*$B$1) -> 232.02327 | D121: =RANDBETWEEN(2*10^7,8*10^7) -> 43827820 | E121: =D121*$B$4 -> 4828426.4 | F121: =(E121)/(8760*$B$1) -> 688.98779 | G121: 0.4 | H121: 0 | I121: 0 | J121: 0 | K121: =C121+H121+F121 -> 921.01106 | L121: 0.15 | M121: =C121+F121 -> 921.01106 | O121: =ROUND((C121+F121)/1000,2) -> 0.92 | P121: =H121/1000 -> 0 | Q121: =K121+L121*K121 -> 1059.1627
A122: Wind_11 | B122: 0.28102853 | C122: =(B122*10^7)/(8760*$B$1) -> 401.01103 | D122: =RANDBETWEEN(2*10^7,8*10^7) -> 40030201 | E122: =D122*$B$4 -> 4410050.1 | F122: =(E122)/(8760*$B$1) -> 629.28797 | G122: 0.43 | H122: 0 | I122: 0 | J122: 0 | K122: =C122+H122+F122 -> 1030.299 | L122: 0.16 | M122: =C122+F122 -> 1030.299 | O122: =ROUND((C122+F122)/1000,2) -> 1.03 | P122: =H122/1000 -> 0 | Q122: =K122+L122*K122 -> 1195.1468
A123: Wind_12 | B123: 0.36279031 | C123: =(B123*10^7)/(8760*$B$1) -> 517.68024 | D123: =RANDBETWEEN(2*10^7,8*10^7) -> 45665660 | E123: =D123*$B$4 -> 5030897.7 | F123: =(E123)/(8760*$B$1) -> 717.87924 | G123: 0.39 | H123: 0 | I123: 0 | J123: 0 | K123: =C123+H123+F123 -> 1235.5595 | L123: 0.18 | M123: =C123+F123 -> 1235.5595 | O123: =ROUND((C123+F123)/1000,2) -> 1.24 | P123: =H123/1000 -> 0 | Q123: =K123+L123*K123 -> 1457.9602
A124: Wind_13 | B124: 0.31738317 | C124: =(B124*10^7)/(8760*$B$1) -> 452.88694 | D124: =RANDBETWEEN(2*10^7,8*10^7) -> 20106932 | E124: =D124*$B$4 -> 2215141.9 | F124: =(E124)/(8760*$B$1) -> 316.08761 | G124: 0.44 | H124: 0 | I124: 0 | J124: 0 | K124: =C124+H124+F124 -> 768.97454 | L124: 0.23 | M124: =C124+F124 -> 768.97454 | O124: =ROUND((C124+F124)/1000,2) -> 0.77 | P124: =H124/1000 -> 0 | Q124: =K124+L124*K124 -> 945.83869
... A129: Wind_18 | B129: 0.43069207 | C129: =(B129*10^7)/(8760*$B$1) -> 614.57201 | D129: =RANDBETWEEN(2*10^7,8*10^7) -> 70448677 | E129: =D129*$B$4 -> 7761194.9 | F129: =(E129)/(8760*$B$1) -> 1107.4764 | G129: 0.29 | H129: 0 | I129: 0 | J129: 0 | K129: =C129+H129+F129 -> 1722.0485 | L129: 0.24 | M129: =C129+F129 -> 1722.0485 | O129: =ROUND((C129+F129)/1000,2) -> 1.72 | P129: =H129/1000 -> 0 | Q129: =K129+L129*K129 -> 2135.3401
...

Sheet Sheet2
B4: Plant | C4: Magrinal cost | D4: Bidding Marginal cost | E4: Bid Vol
B5: ='Fixed cost calculation'!A8 -> Coal_1 | C5: ='Fixed cost calculation'!K8 -> 3309.7155 | D5: ='Fixed cost calculation'!Q8 -> 3806.1728 | E5: v1 | F5: ?
B6: ='Fixed cost calculation'!A9 -> Coal_2 (lignite) | C6: ='Fixed cost calculation'!K9 -> 3659.9796 | D6: ='Fixed cost calculation'!Q9 -> 4062.5773 | E6: v2
B7: ='Fixed cost calculation'!A10 -> Coal_3 (lignite) | C7: ='Fixed cost calculation'!K10 -> 3983.1556 | D7: ='Fixed cost calculation'!Q10 -> 4461.1342 | E7: v3
B8: ='Fixed cost calculation'!A11 -> Coal_4 (imported) | C8: ='Fixed cost calculation'!K11 -> 3686.9211 | D8: ='Fixed cost calculation'!Q11 -> 4239.9592 | E8: v4
B9: ='Fixed cost calculation'!A12 -> Coal_5 | C9: ='Fixed cost calculation'!K12 -> 3709.0437 | D9: ='Fixed cost calculation'!Q12 -> 4191.2193 | E9: v5
B10: ='Fixed cost calculation'!A13 -> Coal_6 | C10: ='Fixed cost calculation'!K13 -> 3577.0892 | D10: ='Fixed cost calculation'!Q13 -> 4006.3399 | E10: v6
B11: ='Fixed cost calculation'!A14 -> Coal_7 | C11: ='Fixed cost calculation'!K14 -> 3285.4695 | D11: ='Fixed cost calculation'!Q14 -> 3712.5806 | E11: v7
B12: ='Fixed cost calculation'!A15 -> Coal_8 | C12: ='Fixed cost calculation'!K15 -> 3332.731 | D12: ='Fixed cost calculation'!Q15 -> 3765.986 | E12: v8
B13: ='Fixed cost calculation'!A16 -> Coal_9 | C13: ='Fixed cost calculation'!K16 -> 3291.888 | D13: ='Fixed cost calculation'!Q16 -> 3719.8335 | E13: v9
B14: ='Fixed cost calculation'!A17 -> Coal_10 | C14: ='Fixed cost calculation'!K17 -> 3333.2951 | D14: ='Fixed cost calculation'!Q17 -> 3799.9564 | E14: v10
B15: ='Fixed cost calculation'!A18 -> Coal_11 | C15: ='Fixed cost calculation'!K18 -> 3439.2518 | D15: ='Fixed cost calculation'!Q18 -> 3886.3546 | E15: v11
B16: ='Fixed cost calculation'!A19 -> Coal_12 | C16: ='Fixed cost calculation'!K19 -> 3385.8653 | D16: ='Fixed cost calculation'!Q19 -> 3724.4519 | E16: v12
B17: ='Fixed cost calculation'!A20 -> Coal_13 | C17: ='Fixed cost calculation'!K20 -> 3400.1062 | D17: ='Fixed cost calculation'!Q20 -> 3774.1179 | E17: v13
... B19: ='Fixed cost calculation'!A22 -> Coal_15 | C19: ='Fixed cost calculation'!K22 -> 3673.1544 | D19: ='Fixed cost calculation'!Q22 -> 4150.6645 | E19: v15
B20: ='Fixed cost calculation'!A25 -> CCGTurbine_1 | C20: ='Fixed cost calculation'!K25 -> 8305.9258 | D20: ='Fixed cost calculation'!Q25 -> 8721.2221 | E20: v16
B21: ='Fixed cost calculation'!A26 -> Gas Turbine_2 | C21: ='Fixed cost calculation'!K26 -> 13406.28 | D21: ='Fixed cost calculation'!Q26 -> 14076.594 | E21: v17
B22: ='Fixed cost calculation'!A27 -> Gas Turbine_3 | C22: ='Fixed cost calculation'!K27 -> 13617.644 | D22: ='Fixed cost calculation'!Q27 -> 14298.526 | E22: v18
B23: ='Fixed cost calculation'!A28 -> Gas Turbine_4 | C23: ='Fixed cost calculation'!K28 -> 10759.89 | D23: ='Fixed cost calculation'!Q28 -> 11297.885 | E23: v19
B24: ='Fixed cost calculation'!A29 -> Gas Turbine_5 | C24: ='Fixed cost calculation'!K29 -> 14489.14 | D24: ='Fixed cost calculation'!Q29 -> 15213.597 | E24: v20
B25: ='Fixed cost calculation'!A30 -> Gas Turbine_6 | C25: ='Fixed cost calculation'!K30 -> 15034.375 | D25: ='Fixed cost calculation'!Q30 -> 15786.094 | E25: v21
B26: ='Fixed cost calculation'!A31 -> Gas Turbine_7 | C26: ='Fixed cost calculation'!K31 -> 10601.42 | D26: ='Fixed cost calculation'!Q31 -> 11131.491 | E26: v22
B27: ='Fixed cost calculation'!A32 -> Gas Turbine_8 | C27: ='Fixed cost calculation'!K32 -> 13858.518 | D27: ='Fixed cost calculation'!Q32 -> 14551.444 | E27: v23
B28: ='Fixed cost calculation'!A33 -> Gas Turbine_9 | C28: ='Fixed cost calculation'!K33 -> 15809.69 | D28: ='Fixed cost calculation'!Q33 -> 16600.175 | E28: v24
B29: ='Fixed cost calculation'!A34 -> Gas Turbine_10 | C29: ='Fixed cost calculation'!K34 -> 10785.603 | D29: ='Fixed cost calculation'!Q34 -> 11324.883 | E29: v25
B30: ='Fixed cost calculation'!A35 -> Gas Turbine_11 | C30: ='Fixed cost calculation'!K35 -> 10793.009 | D30: ='Fixed cost calculation'!Q35 -> 11332.659 | E30: v26
B31: ='Fixed cost calculation'!A36 -> CCGTurbine_2 | C31: ='Fixed cost calculation'!K36 -> 8170.2831 | D31: ='Fixed cost calculation'!Q36 -> 8578.7972 | E31: v27
... B39: ='Fixed cost calculation'!A44 -> Gas Turbine_20 | C39: ='Fixed cost calculation'!K44 -> 8350.8185 | D39: ='Fixed cost calculation'!Q44 -> 8768.3594 | E39: v35
B40: ='Fixed cost calculation'!A51 -> Hydro_1 | C40: ='Fixed cost calculation'!K51 -> 2217.178 | D40: ='Fixed cost calculation'!Q51 -> 2549.7547 | E40: v36
B41: ='Fixed cost calculation'!A52 -> Hydro_2 | C41: ='Fixed cost calculation'!K52 -> 1079.7678 | D41: ='Fixed cost calculation'!Q52 -> 1284.9237 | E41: v37
B42: ='Fixed cost calculation'!A53 -> Hydro_3 | C42: ='Fixed cost calculation'!K53 -> 1934.9935 | D42: ='Fixed cost calculation'!Q53 -> 2167.1927 | E42: v38
B43: ='Fixed cost calculation'!A54 -> Hydro_4 | C43: ='Fixed cost calculation'!K54 -> 2280.3857 | D43: ='Fixed cost calculation'!Q54 -> 2531.2281 | E43: v39
B44: ='Fixed cost calculation'!A55 -> Hydro_5 | C44: ='Fixed cost calculation'!K55 -> 1331.6614 | D44: ='Fixed cost calculation'!Q55 -> 1664.5768 | E44: v40
B45: ='Fixed cost calculation'!A56 -> Hydro_6 | C45: ='Fixed cost calculation'!K56 -> 1655.9384 | D45: ='Fixed cost calculation'!Q56 -> 2020.2449 | E45: v41
B46: ='Fixed cost calculation'!A57 -> Hydro_7 | C46: ='Fixed cost calculation'!K57 -> 1776.6773 | D46: ='Fixed cost calculation'!Q57 -> 1954.345 | E46: v42
B47: ='Fixed cost calculation'!A58 -> Hydro_8 | C47: ='Fixed cost calculation'!K58 -> 1885.8928 | D47: ='Fixed cost calculation'!Q58 -> 2112.2 | E47: v43
B48: ='Fixed cost calculation'!A59 -> Hydro_9 | C48: ='Fixed cost calculation'!K59 -> 1463.3265 | D48: ='Fixed cost calculation'!Q59 -> 1770.6251 | E48: v44
B49: ='Fixed cost calculation'!A60 -> Hydro_10 | C49: ='Fixed cost calculation'!K60 -> 1293.3716 | D49: ='Fixed cost calculation'!Q60 -> 1526.1784 | E49: v45
B50: ='Fixed cost calculation'!A61 -> Hydro_11 | C50: ='Fixed cost calculation'!K61 -> 1685.0161 | D50: ='Fixed cost calculation'!Q61 -> 2106.2702 | E50: v46
B51: ='Fixed cost calculation'!A62 -> Hydro_12 | C51: ='Fixed cost calculation'!K62 -> 2005.5247 | D51: ='Fixed cost calculation'!Q62 -> 2226.1324 | E51: v47
... B53: ='Fixed cost calculation'!A64 -> Hydro_14 | C53: ='Fixed cost calculation'!K64 -> 1437.2826 | D53: ='Fixed cost calculation'!Q64 -> 1609.7565 | E53: v49
B54: ='Fixed cost calculation'!A67 -> Solar_1 | C54: ='Fixed cost calculation'!K67 -> 898.84074 | D54: ='Fixed cost calculation'!Q67 -> 1006.7016 | E54: v50
B55: ='Fixed cost calculation'!A68 -> Solar_2 | C55: ='Fixed cost calculation'!K68 -> 1202.3079 | D55: ='Fixed cost calculation'!Q68 -> 1418.7234 | E55: v51
B56: ='Fixed cost calculation'!A69 -> Solar_3 | C56: ='Fixed cost calculation'!K69 -> 938.59602 | D56: ='Fixed cost calculation'!Q69 -> 1079.3854 | E56: v52
B57: ='Fixed cost calculation'!A70 -> Solar_4 | C57: ='Fixed cost calculation'!K70 -> 980.41787 | D57: ='Fixed cost calculation'!Q70 -> 1107.8722 | E57: v53
B58: ='Fixed cost calculation'!A71 -> Solar_5 | C58: ='Fixed cost calculation'!K71 -> 947.67057 | D58: ='Fixed cost calculation'!Q71 -> 1061.391 | E58: v54
B59: ='Fixed cost calculation'!A72 -> Solar_6 | C59: ='Fixed cost calculation'!K72 -> 950.40381 | D59: ='Fixed cost calculation'!Q72 -> 1168.9967 | E59: v55
B60: ='Fixed cost calculation'!A73 -> Solar_7 | C60: ='Fixed cost calculation'!K73 -> 946.98018 | D60: ='Fixed cost calculation'!Q73 -> 1126.9064 | E60: v56
B61: ='Fixed cost calculation'!A74 -> Solar_8 | C61: ='Fixed cost calculation'!K74 -> 858.74566 | D61: ='Fixed cost calculation'!Q74 -> 961.79514 | E61: v57
B62: ='Fixed cost calculation'!A75 -> Solar_9 | C62: ='Fixed cost calculation'!K75 -> 964.82982 | D62: ='Fixed cost calculation'!Q75 -> 1186.7407 | E62: v58
B63: ='Fixed cost calculation'!A76 -> Solar_10 | C63: ='Fixed cost calculation'!K76 -> 840.16541 | D63: ='Fixed cost calculation'!Q76 -> 1016.6001 | E63: v59
B64: ='Fixed cost calculation'!A77 -> Solar_11 | C64: ='Fixed cost calculation'!K77 -> 975.45149 | D64: ='Fixed cost calculation'!Q77 -> 1121.7692 | E64: v60
B65: ='Fixed cost calculation'!A78 -> Solar_12 | C65: ='Fixed cost calculation'!K78 -> 882.008 | D65: ='Fixed cost calculation'!Q78 -> 1031.9494 | E65: v61
... B82: ='Fixed cost calculation'!A95 -> Solar_29 | C82: ='Fixed cost calculation'!K95 -> 918.52829 | D82: ='Fixed cost calculation'!Q95 -> 1074.6781 | E82: v78
B83: ='Fixed cost calculation'!A98 -> Nuclear_1 | C83: ='Fixed cost calculation'!K98 -> 3479.1572 | D83: ='Fixed cost calculation'!Q98 -> 4244.5718 | E83: v79
B84: ='Fixed cost calculation'!A99 -> Nuclear_2 | C84: ='Fixed cost calculation'!K99 -> 4059.1635 | D84: ='Fixed cost calculation'!Q99 -> 4505.6715 | E84: v80
B85: ='Fixed cost calculation'!A100 -> Nuclear_3 | C85: ='Fixed cost calculation'!K100 -> 3860.2249 | D85: ='Fixed cost calculation'!Q100 -> 4670.8721 | E85: v81
B86: ='Fixed cost calculation'!A101 -> Nuclear_4 | C86: ='Fixed cost calculation'!K101 -> 3860.8781 | D86: ='Fixed cost calculation'!Q101 -> 4324.1835 | E86: v82
B87: ='Fixed cost calculation'!A102 -> Nuclear_5 | C87: ='Fixed cost calculation'!K102 -> 3329.9763 | D87: ='Fixed cost calculation'!Q102 -> 3829.4728 | E87: v83
B88: ='Fixed cost calculation'!A103 -> Nuclear_6 | C88: ='Fixed cost calculation'!K103 -> 3984.4868 | D88: ='Fixed cost calculation'!Q103 -> 4701.6945 | E88: v84
B89: ='Fixed cost calculation'!A104 -> Nuclear_7 | C89: ='Fixed cost calculation'!K104 -> 3886.42 | D89: ='Fixed cost calculation'!Q104 -> 4391.6546 | E89: v85
B90: ='Fixed cost calculation'!A105 -> Nuclear_8 | C90: ='Fixed cost calculation'!K105 -> 3424.3041 | D90: ='Fixed cost calculation'!Q105 -> 4074.9218 | E90: v86
B91: ='Fixed cost calculation'!A106 -> Nuclear_9 | C91: ='Fixed cost calculation'!K106 -> 3395.8537 | D91: ='Fixed cost calculation'!Q106 -> 3939.1903 | E91: v87
B92: ='Fixed cost calculation'!A107 -> Nuclear_10 | C92: ='Fixed cost calculation'!K107 -> 3715.8564 | D92: ='Fixed cost calculation'!Q107 -> 4533.3449 | E92: v88
B93: ='Fixed cost calculation'!A108 -> Nuclear_11 | C93: ='Fixed cost calculation'!K108 -> 3504.9501 | D93: ='Fixed cost calculation'!Q108 -> 3925.5441 | E93: v89
B94: ='Fixed cost calculation'!A109 -> Nuclear_12 | C94: ='Fixed cost calculation'!K109 -> 3293.9255 | D94: ='Fixed cost calculation'!Q109 -> 4084.4676 | E94: v90
B95: ='Fixed cost calculation'!A112 -> Wind_1 | C95: ='Fixed cost calculation'!K112 -> 1144.0059 | D95: ='Fixed cost calculation'!Q112 -> 1292.7267 | E95: v91
B96: ='Fixed cost calculation'!A113 -> Wind_2 | C96: ='Fixed cost calculation'!K113 -> 1402.652 | D96: ='Fixed cost calculation'!Q113 -> 1669.1559 | E96: v92
B97: ='Fixed cost calculation'!A114 -> Wind_3 | C97: ='Fixed cost calculation'!K114 -> 1341.8661 | D97: ='Fixed cost calculation'!Q114 -> 1623.6579 | E97: v93
B98: ='Fixed cost calculation'!A115 -> Wind_4 | C98: ='Fixed cost calculation'!K115 -> 1150.7702 | D98: ='Fixed cost calculation'!Q115 -> 1369.4166 | E98: v94
B99: ='Fixed cost calculation'!A116 -> Wind_5 | C99: ='Fixed cost calculation'!K116 -> 1808.3001 | D99: ='Fixed cost calculation'!Q116 -> 2079.5451 | E99: v95
B100: ='Fixed cost calculation'!A117 -> Wind_6 | C100: ='Fixed cost calculation'!K117 -> 1243.509 | D100: ='Fixed cost calculation'!Q117 -> 1430.0354 | E100: v96
B101: ='Fixed cost calculation'!A118 -> Wind_7 | C101: ='Fixed cost calculation'!K118 -> 848.29112 | D101: ='Fixed cost calculation'!Q118 -> 1051.881 | E101: v97
B102: ='Fixed cost calculation'!A119 -> Wind_8 | C102: ='Fixed cost calculation'!K119 -> 1586.5723 | D102: ='Fixed cost calculation'!Q119 -> 1967.3496 | E102: v98
B103: ='Fixed cost calculation'!A120 -> Wind_9 | C103: ='Fixed cost calculation'!K120 -> 1356.5218 | D103: ='Fixed cost calculation'!Q120 -> 1654.9567 | E103: v99
B104: ='Fixed cost calculation'!A121 -> Wind_10 | C104: ='Fixed cost calculation'!K121 -> 921.01106 | D104: ='Fixed cost calculation'!Q121 -> 1059.1627 | E104: v100
B105: ='Fixed cost calculation'!A122 -> Wind_11 | C105: ='Fixed cost calculation'!K122 -> 1030.299 | D105: ='Fixed cost calculation'!Q122 -> 1195.1468 | E105: v101
B106: ='Fixed cost calculation'!A123 -> Wind_12 | C106: ='Fixed cost calculation'!K123 -> 1235.5595 | D106: ='Fixed cost calculation'!Q123 -> 1457.9602 | E106: v102
B107: ='Fixed cost calculation'!A124 -> Wind_13 | C107: ='Fixed cost calculation'!K124 -> 768.97454
B108: ='Fixed cost calculation'!A125 -> Wind_14 | C108: ='Fixed cost calculation'!K125 -> 623.32965
B109: ='Fixed cost calculation'!A126 -> Wind_15 | C109: ='Fixed cost calculation'!K126 -> 492.19515
B110: ='Fixed cost calculation'!A127 -> Wind_16 | C110: ='Fixed cost calculation'!K127 -> 1330.6824
B111: ='Fixed cost calculation'!A128 -> Wind_17 | C111: ='Fixed cost calculation'!K128 -> 2207.0466
B112: ='Fixed cost calculation'!A129 -> Wind_18 | C112: ='Fixed cost calculation'!K129 -> 1722.0485
B113: ='Fixed cost calculation'!A130 -> 0
B114: ='Fixed cost calculation'!A131 -> Biomass
B115: ='Fixed cost calculation'!A132 -> 0

Sheet Cost Range
A1: Technology | B1: Size (1 Unit) MW | C1: Electrical Efficiency | D1: Capital cost (cr. ₹/MW) | E1: Fixed O&M (cr. ₹/MW/year) | F1: Variable O&M (₹/MWh) | G1: Hot Startup cost (cr.₹/MW/startup) | H1: Warm Startup cost (cr.₹/MW/startup) | I1: Cold Startup cost (cr.₹/MW/startup)
A2: Coal | B2: 210-600 | C2: 0.36 | D2: 9.2 | E2: 0.27 | G2: 25000 | H2: 30000 | I2: 52000
B3: 660-800 | C3: 0.38 | D3: 8.3 | E3: 0.2 | G3: 25000 | H3: 30000 | I3: 52000
B4: 660-800 | C4: 0.413 | D4: 8.4 | E4: 0.2
A6: Gas Power | B6: 50-200+ | C6: 0.28 | D6: 5 | E6: 0.18 | G6: 2473
B7: 50-870 | C7: 0.6 | D7: 3.47 | E7: 0.29 | G7: 1556 | H7: 7782 | I7: 12451
B8: 10 | C8: 0.45 | D8: 4.1 | E8: 0.07 | F8: 557
A10: Bio Mass | B10: 10 | C10: 0.265 | D10: 5 | E10: 0.1 | G10: 2217 | H10: 3325 | I10: 4433
A12: Wind Turbine onshore | B12: 2.5 | D12: 6.66 | E12: 0.068 | F12: 240
A13: Wind turbines, offshore | B13: 8 | D13: 23.1 | E13: 0.674
A15: PV | B15: 50-150 | D15: 5.4 | E15: 0.035
A17: Hydro Power Plants Run-of-river without storage | B17: 35-120 | C17: 0.973 | D17: 10.7 | E17: 0.44
A18: Hydro power plants, ROR with storage | B18: 20-250 | C18: 0.98 | D18: 11.9 | E18: 0.41
A19: Small Hydro power plants, reservoir (<25 MW) | B19: 1-5 | C19: 0.45 | D19: 8.04 | E19: 0.24
A21: Large Hydro power plants, reservoir (>25 MW) | B21: 35 - 200 | C21: 0.969 | D21: 8.3 | E21: 0.91
A22: Hydro power plants, Pumped storage on-river | D22: 6 | E22: 0.15
A23: Hydro power plants, Pumped storage closed loop | D23: 3.85 | E23: 0.1
A25: Nuclear power plant, Pressurized heavy-water reactor | B25: 460 | C25: 0.31 | D25: 11.7 | E25: 0.43
A26: Nuclear power plant, Light-water Reactor | B26: 1000 - 1600 | C26: 0.31 | D26: 19 | E26: 0.26
A28: BESS | B28: 1-100 | C28: 0.9 | D28: 6.73 | E28: 0.08 | F28: 500

Sheet Sheet1
A2: Technology | B2: average (Fixed O&M (cr. ₹/MW/year) | C2: Fixed Cost in ₹/MWh | D2: CAPEX ( ₹/MW) | E2: Annual CAPEX ( ₹/MW) | F2: Annual CAPEX ( ₹/MWh) | G2: Efficiency | H2: Fuel Price | I2: CO2 cost | J2: Magrinal cost | K2: Profit Margin | L2: Additional Cost | M2: Variable cost | N2: Bidding Marginal cost
A3: Solar | B3: 0.035 | C3: 49.942922 | D3: 54000000 | E3: 5949075.9 | F3: 848.89782 | G3: 0.23 | H3: 0 | I3: 0 | J3: 898.84074 | K3: 0.1 | L3: 0.89884074 | M3: 0 | N3: 988.72481
A4: Wind | B4: 0.068 | C4: 97.031963 | D4: 66600000 | E4: 7337193.6 | F4: 1046.974 | G4: 0.35 | H4: 0 | I4: 0 | J4: 1144.0059 | K4: 0.2 | L4: 1.1440059 | M4: 0 | N4: 1372.8071
A5: Hydro | B5: 0.375 | C5: 535.10274 | D5: 107000000 | E5: 11787984 | F5: 1682.0753 | G5: 0.8 | H5: 0 | I5: 0 | J5: 2217.178 | K5: 0.2 | L5: 2.217178 | M5: 0 | N5: 2660.6137
A6: Coal | B6: 0.22333333 | C6: 318.68341 | D6: 86000000 | E6: 9474454.2 | F6: 1351.9484 | G6: 0.35 | H6: 1712.9121 | I6: 0 | J6: 3383.5439 | K6: 0.1 | L6: 1.6706318 | M6: 1.7129121 | N6: 3721.8983
A7: Coal | B7: 0.27 | C7: 385.27397 | D7: 92000000 | E7: 10135463 | F7: 1446.2704 | G7: 0.32 | H7: 1873.4976 | I7: 0 | J7: 3705.0419 | K7: 0.1 | L7: 1.8315443 | M7: 1.8734976 | N7: 4075.5461
A8: Nuclear | B8: 0.345 | C8: 492.29452 | D8: 190000000 | E8: 20931934 | F8: 2986.8627 | G8: 0.45 | H8: 0 | I8: 0 | J8: 3479.1572 | K8: 0.2 | L8: 3.4791572 | M8: 0 | N8: 4174.9887
A9: Gas Turbine | B9: 0.18 | C9: 256.84932 | D9: 50000000 | E9: 5508403.6 | F9: 786.0165 | G9: 0.38 | H9: 2784.7699 | I9: 0 | J9: 3827.6357 | K9: 0.15 | L9: 1.0428658 | M9: 2.7847699 | N9: 4401.781

Sheet Financial Parameters Generators
A1: Data Source | B1: https://drive.google.com/file/d/1HcrTbXi6cDYhCJUCOnkTY3b5tOywMZJf/view?usp=sharing
A3: Technology | B3: Capital cost (cr. ₹/MW) | C3: Fixed O&M (cr. ₹/MW/year)
D4: Hot Startup cost (cr. ₹/MW/startup) | E4: Warm Startup cost (cr. ₹/MW/startup) | F4: Codl Startup cost (cr. ₹/MW/startup) | G4: Variable O &M Cost (₹/MWh)
A5: Pulverized coal fired, subcritical steam process, condensing plant | B5: 9.2 | C5: 0.27 | D5: 25000 | E5: 30000 | F5: 52000
A6: 01b Pulverized coal fired, supercritical steam process, condensing plant | B6: 8.3 | C6: 0.2 | D6: 25000 | E6: 30000 | F6: 52000
A7: 01c Pulverized coal fired, ultra-supercritical steam process, condensing plant | B7: 8.4 | C7: 0.2 | D7: - | E7: - | F7: - | G7: -
A8: 02a Gas turbine, open cycle (large), back pressure | B8: 5 | C8: 0.18 | D8: 2473 | E8: - | F8: - | G8: -
A9: 02b Gas turbine, combined cycle, condensing plant | B9: 3.47 | C9: 0.29 | D9: 1556 | E9: 7782 | F9: 12451 | G9: 0.21
A10: 02c Gas Engine | B10: 4.1 | C10: 0.07 | D10: - | E10: - | F10: - | G10: 557
A11: 03 Biomass plant | B11: 5 | C11: 0.1 | D11: 2217 | E11: 3325 | F11: 4433
A12: 04 Large wind turbines on land | B12: 6.66 | C12: 0.068 | D12: - | E12: - | F12: - | G12: 240
A13: 05 Large wind turbines offshore | B13: 23.1 | C13: 0.674 | D13: - | E13: - | F13: - | G13: -
A14: 06a Photovoltaics: Large scale utility systems | B14: 5.4 | C14: 0.035
A15: 06b Photovoltaics: Rooftop System | B15: 3.9 | C15: 0.051
A16: 07a Hydro power plants, Run-of-river without storage | B16: 10.7 | C16: 0.44
A17: 07b Hydro power plants, ROR with storage | B17: 11.9 | C17: 0.41
A18: 07c Small Hydro power plants, reservoir (<25 MW) | B18: 8.04 | C18: 0.24
A19: 07d Large Hydro power plants, reservoir (>25 MW) | B19: 8.3 | C19: 0.91
A20: 07e Hydro power plants, Pumped storage on-river | B20: 6 | C20: 0.15
A21: 7f Hydro power plants, Pumped storage closed loop | B21: 3.85 | C21: 0.1
A22: 08a Nuclear power plant, Pressurized heavy-water reactor | B22: 11.7 | C22: 0.43
A23: 08b Nuclear power plant, Light-water Reactor | B23: 19 | C23: 0.26
A24: 09 Battery storage system (Lithium-ion) | C24: 0.08 | G24: 500

Sheet Renewable share
A1: Source | C1: https://drive.google.com/file/d/1H94p2NGkwG1ykCGv09jNeb_6l2uJo5o5/view?usp=sharing
A2: Data as of | B2: 45778
A3: Total | B3: =SUM(B4:B7) -> 172.37
A4: Solar | B4: 105.65 | C4: GW
A5: BioMass | B5: 11.58 | C5: GW
A6: Wind | B6: 50.04 | C6: GW
A7: Small Hydro | B7: 5.1 | C7: GW
A10: Solar+Wind | B10: 155.69
A11: Solar/Wind | B11: =B4/B6 -> 2.111311
A13: If solar +wind = | B13: 297.128 | C13: MW
A14: and Solar/Wind = | B14: =B11 -> 2.111311
A15: Then
A16: Solar =
A17: Wind =
A19: Wind = | B19: =B13/(B14+1) -> 95.499294 | C19: MW
A20: Solar = | B20: =B13-B19 -> 201.62871 | C20: MW

Sheet Coal Prices
A1: Source | C1: https://drive.google.com/file/d/1hU4YMXpBnXoH4fNPDDoh5U8MwEvjewMP/view?usp=sharing
C2: https://drive.google.com/file/d/11_-cSwfuGbUOeZDIztLrIDRQaRhIc73M/view?usp=sharing
B3: Rs/ton | C3: Rs/ton
A4: Grade | B4: 46143 | C4: 46174 | D4: kCal/kg | F4: For Grade 7 Coal | H4: between 5200 to 5500 | I4: kCal/kg
A5: G1 | B5: 11228 | C5: 10701 | D5: Exceeding 7000 | F5: Energy Content | H5: 5200 | I5: kCal/kg | K5: Energy Content(MWh per ton) | N5: (kCal/kg)*1000/860000
A6: G2 | B6: 7014 | C6: 7280 | F6: Energy Content | H6: =H5*1000/860000 -> 6.0465116 | I6: MWh/ton
A7: G3 | B7: 6610 | C7: 6882
A8: G4 | B8: 6502 | C8: 6834 | F8: Coal cost (₹/MWh) | H8: Coal Price/Energy Content(MWh per ton)
A9: G5 | B9: 6242 | C9: 6541 | H9: =$C$11/H6 -> 599.51923 | I9: ₹/MWh
A10: G6 | B10: 5699 | C10: 5952
A11: G7 | B11: 3483 | C11: 3625 | D11: Exceeding 5200 and not exceeding 5500
A12: G8 | B12: 3224 | C12: 3385 | D12: Exceeding 4900 and not exceeding 5200 | F12: Energy Content | H12: 5500 | I12: kCal/kg
A13: G9 | B13: 2837 | C13: 2912 | D13: 4800 | F13: Energy Content | H13: =H12*1000/860000 -> 6.3953488 | I13: MWh/ton
A14: G10 | B14: 2638 | C14: 2735
A15: G11 | B15: 1969 | C15: 2084 | F15: Coal cost (₹/MWh) | H15: Coal Price/Energy Content(MWh per ton)
A16: G12 | B16: 1744 | C16: 1858 | H16: =$C$11/H13 -> 566.81818 | I16: ₹/MWh
A17: G13 | B17: 1716 | C17: 1849 | F17: Energy Content Lignite | H17: 4800 | I17: kCal/kg
A18: G14 | B18: 1429 | C18: 1511
A19: G15 | B19: 1009 | C19: 1009 | F19: For Grade 8 Coal | H19: between 4900 to 5200 | I19: kCal/kg
A20: G16 | B20: 753 | C20: 753 | F20: Energy Content | H20: 4900 | I20: kCal/kg
A21: G17 | B21: 669 | C21: 669 | F21: Energy Content | H21: =H20*1000/860000 -> 5.6976744 | I21: MWh/ton
A22: ST-I | B22: 22220 | C22: 23153
A23: ST-II | B23: 20175 | C23: 21021 | F23: Coal cost (₹/MWh) | H23: Coal Price/Energy Content(MWh per ton)
A24: W-I | B24: 4854 | C24: 4762 | H24: =$C$12/H21 -> 594.10204 | I24: ₹/MWh
A25: W-II | B25: 4486 | C25: 4202
A26: W-III | B26: 3732 | C26: 3531 | F26: For Grade 8 Coal | H26: between 4900 to 5200 | I26: kCal/kg
A27: W-IV | B27: 3003 | C27: 2999 | F27: Energy Content | H27: 5200 | I27: kCal/kg
F28: Energy Content | H28: =H27*1000/860000 -> 6.0465116 | I28: MWh/ton
F30: Coal cost (₹/MWh) | H30: Coal Price/Energy Content(MWh per ton)
H31: =$C$12/H28 -> 559.82692 | I31: ₹/MWh

Sheet Gas Price
A1: Source | C1: https://ppac.gov.in/natural-gas/gas-price?page=1
A3: Gas Price | B3: 7 | C3: US$/MMBTU | F3: 1MMBtu = 1.055 GJ = 0.293 MWh
B4: =B3*95.08 -> 665.56 | C4: ₹//MMBTU | F4: Exchange Rate 1US $ = 95.08 ₹
F5: 1 MMBtu=252,000 kcal
A6: Heat rate | B6: 3071 | C6: (MCal/MWh) | D6: =B6*1000 -> 3071000 | E6: kCal/MWh
B7: 1423 | C7: (MCal/MWh) | D7: =B7*1000 -> 1423000 | E7: kCal/MWh
B8: 1868 | C8: (MCal/MWh) | D8: =B8*1000 -> 1868000 | E8: kCal/MWh
B10: =D6/252000 -> 12.186508
B11: =B3*B10 -> 85.305556
B12: =B11/0.5 -> 170.61111

Sheet Hydro availability Factor
A1: Source | C1: https://npp.gov.in/dgrReports
A3: https://npp.gov.in/public-reports/cea/daily/dgr/02-07-2026/dgr1-2026-07-02.pdf
A4: https://npp.gov.in/public-reports/cea/daily/dgr/03-07-2026/dgr1-2026-07-03.pdf
A8: https://npp.gov.in/public-reports/cea/daily/dgr/01-07-2026/dgr1-2026-07-01.pdf
A9: https://npp.gov.in/public-reports/cea/daily/dgr/02-07-2026/dgr1-2026-07-02.pdf
A10: https://npp.gov.in/public-reports/cea/daily/dgr/03-07-2026/dgr1-2026-07-03.pdf
A11: https://npp.gov.in/public-reports/cea/daily/dgr/04-07-2026/dgr1-2026-07-04.pdf
A12: https://npp.gov.in/public-reports/cea/daily/dgr/05-07-2026/dgr1-2026-07-05.pdf
A13: https://npp.gov.in/public-reports/cea/daily/dgr/06-07-2026/dgr1-2026-07-06.pdf
A14: https://npp.gov.in/public-reports/cea/daily/dgr/07-07-2026/dgr1-2026-07-07.pdf
A15: https://npp.gov.in/public-reports/cea/daily/dgr/08-07-2026/dgr1-2026-07-08.pdf
A16: https://npp.gov.in/public-reports/cea/daily/dgr/09-07-2026/dgr1-2026-07-09.pdf
A17: https://npp.gov.in/public-reports/cea/daily/dgr/10-07-2026/dgr1-2026-07-10.pdf
... A38: https://npp.gov.in/public-reports/cea/daily/dgr/31-07-2026/dgr1-2026-07-31.pdf

Sheet Solar availability factor
A1: Source | C1: https://iced.niti.gov.in/energy/fuel-sources/solar/irradiance

Sheet Wind availbility factor
A1: Source | C1: https://iced.niti.gov.in/energy/fuel-sources/solar/irradiance
